hypno/api.py
hypno/injection.cpython-39-x86_64-linux-gnu.so
hypno/__init__.py
hypno/__main__.py
hypno-1.1.0.dist-info/LICENSE.txt
hypno-1.1.0.dist-info/METADATA
hypno-1.1.0.dist-info/RECORD
hypno-1.1.0.dist-info/top_level.txt
hypno-1.1.0.dist-info/entry_points.txt
hypno-1.1.0.dist-info/WHEEL
