Metadata-Version: 2.1
Name: hypno
Version: 1.1.0
Summary: A tool/library allowing to inject python code into a running python process.
Home-page: https://github.com/kmaork/hypno
Author: Maor Kleinberger
Author-email: kmaork@gmail.com
Keywords: injection library
Classifier: Intended Audience :: Developers
Classifier: License :: OSI Approved :: MIT License
Classifier: Programming Language :: Python :: 3
Classifier: Programming Language :: Python :: 3 :: Only
Classifier: Programming Language :: Python :: 3.8
Classifier: Programming Language :: Python :: 3.9
Classifier: Programming Language :: Python :: 3.10
Classifier: Programming Language :: Python :: 3.11
Classifier: Topic :: Software Development :: Libraries :: Python Modules
Requires-Python: >=3.7
License-File: LICENSE.txt
Requires-Dist: pyinjector >=0.1.2
